Workbook

Sheet Summary
A1: CloudScale incident platform: 3-year TCO / ROI
A2: All figures are formulas over the Inputs and Token Economics sheets.
A4: Year | B4: Platform cost | C4: Benefit | D4: Net | E4: Cumulative | F4: Discount factor | G4: Present value
A5: Y0 | B5: =TCO!B17 | C5: =0 | D5: =C5-B5 | E5: =D5 | F5: =1/(1+Inputs!$B$18)^0 | G5: =D5*F5
A6: Y1 | B6: =TCO!B10 | C6: =Benefits!B14 | D6: =C6-B6 | E6: =E5+D6 | F6: =1/(1+Inputs!$B$18)^1 | G6: =D6*F6
A7: Y2 | B7: =TCO!C10 | C7: =Benefits!C14 | D7: =C7-B7 | E7: =E6+D7 | F7: =1/(1+Inputs!$B$18)^2 | G7: =D7*F7
A8: Y3 | B8: =TCO!D10 | C8: =Benefits!D14 | D8: =C8-B8 | E8: =E7+D8 | F8: =1/(1+Inputs!$B$18)^3 | G8: =D8*F8
A9: 3-year total | B9: =SUM(B5:B8) | C9: =SUM(C5:C8) | D9: =SUM(D5:D8) | G9: =SUM(G5:G8)
A11: NPV (10 %) | B11: =G9
A12: 3-year net | B12: =E8
A13: Benefit-cost ratio | B13: =IF(B9=0,0,C9/B9)
A14: Net ROI | B14: =IF(B9=0,0,E8/B9)
A15: Payback (month of operation) | B15: =IF(E6>=0,ROUNDUP(-E5/(D6/12),0),IF(E7>=0,12+ROUNDUP(-E6/(D7/12),0),IF(E8>=0,24+ROUNDUP(-E7/(D8/12),0),"> 36")))
A16: LLM share of 3-year cost | B16: =(SUM(TCO!B6:D7)*12)/B9
A17: LLM cost per incident (as built, measured on OpenAI) | B17: ='Token Economics'!B45
A18: LLM cost per SRE-minute saved (automated path) | B18: =B17/Inputs!B11
A19: SRE hours freed, Y1 / Y3 | B19: =TEXT(Benefits!B13*12,"#,##0")&" h / "&TEXT(Benefits!D13*12,"#,##0")&" h"

Sheet Inputs
A1: Inputs and assumptions
A2: Blue = input you can change · black = formula · green = link to another sheet. Source: CapstoneProjectPlan_v2.md §17 unless noted.
A3: Assumption | B3: Y1 | C3: Y2 | D3: Y3 | E3: Note
A4: SRE fully loaded rate ($/h) | B4: 150 | E4: Blueprint §17.1
A5: Incidents per month, Y1 | B5: 200 | E5: Blueprint §17.1
A6: Incident growth per year | B6: 0.3 | E6: +30 % YoY
A7: Share of incidents routed through the platform | B7: 0.7 | C7: 0.9 | D7: 0.95 | E7: Adoption ramp; v1 assumed 100 % on day 1
A8: Outcome mix: automated | B8: 0.4 | C8: 0.5 | D8: 0.55 | E8: Informed by the scenario gate mix
A9: Outcome mix: human-approved (HITL) | B9: 0.4 | C9: 0.35 | D9: 0.32
A10: Outcome mix: escalated | B10: =1-B8-B9 | C10: =1-C8-C9 | D10: =1-D8-D9 | E10: Remainder of the mix
A11: Minutes saved per automated incident | B11: 38 | E11: 45 min manual MTTR -> ~7 min incl. post-review
A12: Minutes saved per HITL incident | B12: 25 | E12: 45 -> 20 min
A13: Minutes saved per escalated incident | B13: 10 | E13: Diagnosis already done when a human picks it up
A14: Bad-remediation rate (automated + HITL) | B14: 0.02 | C14: 0.02 | D14: 0.015 | E14: Share that makes things worse
A15: Extra minutes per bad remediation | B15: 120 | E15: Cost of cleaning up a bad fix
A16: Platform maintenance (hours / month) | B16: 20 | C16: 20 | D16: 16 | E16: 20 h x $150 = $3,000 / month
A17: LLM evaluation + staging ($ / month) | B17: 100 | E17: Prompt iteration, eval runs
A18: Discount rate | B18: 0.1
A19: Azure warm DR ($ / month, sensitivity only) | B19: 500 | E19: ADR-007
A21: Year 0 (one-time)
A22: Capstone build (hours) | B22: 24 | E22: Actual: 1 developer + Claude, 2 days (~24 h). Blueprint assumed 10 engineers x 12 h = 120 h
A23: Productionization ($): real K8s/cloud adapters, OIDC, mesh mTLS, pen test | B23: 72000 | E23: 2 engineers x 6 weeks x $150/h
A24: Cloud landing zone + hardening ($) | B24: 2000
A25: Policy authoring + review: OPA, gate policy ($) | B25: 1500
A27: Infrastructure ($ / month, AWS EKS us-east-1 on-demand estimates)
A28: EKS control plane | B28: 73 | C28: 73 | D28: 73 | E28: Validate with the AWS Pricing Calculator before external use (ADR-007)
A29: App node group (m6i.large x3/4/5) | B29: 210 | C29: 280 | D29: 350
A30: Guard node (c6i.xlarge, Llama Guard) | B30: 124 | C30: 124 | D30: 124
A31: RDS PostgreSQL (db.t4g.medium, Multi-AZ, 50 GB) | B31: 105 | C31: 105 | D31: 105
A32: ElastiCache Redis (cache.t4g.medium) | B32: 47 | C32: 47 | D32: 47
A33: Networking (ALB + NAT + egress) | B33: 70 | C33: 70 | D33: 70
A34: Observability storage (30-day) | B34: 40 | C34: 40 | D34: 40
A35: Logs, registry, secrets | B35: 20 | C35: 20 | D35: 20
A38: Sensitivity levers
A39: Lower automation: points shifted automated -> HITL | B39: 0.15
A40: Slower adoption case | B40: 0.5 | C40: 0.7 | D40: 0.75
A41: Lower volume case: incident cut | B41: 0.3

Sheet Token Economics
A1: Token economics per incident
A2: Anthropic first-party list prices per 1M tokens (verify before use). Thinking tokens bill as output.
A4: Model | B4: Input $/1M | C4: Output $/1M
A5: claude-sonnet-5 | B5: 2 | C5: 10
A6: claude-haiku-4-5 | B6: 1 | C6: 5
A8: Agent (average tokens per call) | B8: Input tokens | C8: Output tokens | D8: Cost on Sonnet 5 | E8: Cost on Haiku 4.5
A9: Triage | B9: 8192 | C9: 2048 | D9: =(B9*$B$5+C9*$C$5)/1000000 | E9: =(B9*$B$6+C9*$C$6)/1000000
A10: Planner | B10: 4096 | C10: 3072 | D10: =(B10*$B$5+C10*$C$5)/1000000 | E10: =(B10*$B$6+C10*$C$6)/1000000
A11: Evaluator summary | B11: 2048 | C11: 1024 | D11: =(B11*$B$5+C11*$C$5)/1000000 | E11: =(B11*$B$6+C11*$C$6)/1000000
A13: Share of P1 incidents | B13: 0.4
A14: Semantic cache hit rate (triage + planner) | B14: 0.2
A15: Overhead multiplier (re-plans, validation retries) | B15: 1.3
A17: Token optimization strategy | B17: P1 $/incident | C17: P2 $/incident | D17: Blended | E17: After cache | F17: With overhead
A18: All Sonnet 5 (no routing, no cache) | B18: =SUM(D9:D11) | C18: =SUM(D9:D11) | D18: =$B$13*B18+(1-$B$13)*C18 | E18: =D18 | F18: =E18*$B$15
A19: Tiered routing (Sonnet for P1, Haiku otherwise) | B19: =D9+D10+E11 | C19: =SUM(E9:E11) | D19: =$B$13*B19+(1-$B$13)*C19 | E19: =D19 | F19: =E19*$B$15
A20: Tiered routing + semantic cache (as built) | B20: =B19 | C20: =C19 | D20: =$B$13*B20+(1-$B$13)*C20 | E20: =D20-$B$14*($B$13*(D9+D10)+(1-$B$13)*(E9+E10)) | F20: =E20*$B$15
A22: Saving vs all-Sonnet | F22: =1-F20/F18
A24: 3-year LLM production cost by strategy | B24: Y1 | C24: Y2 | D24: Y3 | E24: 3-year total
A25: All Sonnet 5 (no routing, no cache) | B25: =TCO!B4*12*$F$18 | C25: =TCO!C4*12*$F$18 | D25: =TCO!D4*12*$F$18 | E25: =SUM(B25:D25)
A26: Tiered routing (Sonnet for P1, Haiku otherwise) | B26: =TCO!B4*12*$F$19 | C26: =TCO!C4*12*$F$19 | D26: =TCO!D4*12*$F$19 | E26: =SUM(B26:D26)
A27: Tiered routing + semantic cache (as built) | B27: =TCO!B4*12*$F$20 | C27: =TCO!C4*12*$F$20 | D27: =TCO!D4*12*$F$20 | E27: =SUM(B27:D27)
A29: Measured on OpenAI (token ledger, live rehearsals)
A30: Measurement | B30: Value | C30: Note
A31: Avg LLM cost, P1 / tier-1 incident (gpt-5.4 triage + planner, mini summary) | B31: 0.0227 | C31: n = 21 incidents
A32: Avg LLM cost, P2 incident (all gpt-5.4-mini) | B32: 0.0055 | C32: n = 7 incidents
A33: Avg LLM cost, semantic-cache hit (summary call only) | B33: 0.0008 | C33: n = 13 incidents
A34: Share of input tokens served from the prompt cache | B34: 0.76 | C34: OpenAI automatic prompt caching
A35: Avg triage call on gpt-5.4 | B35: 0.00576 | C35: measured per call
A36: Avg planner call on gpt-5.4 | B36: 0.01606 | C36: measured per call
A37: Avg summary call: input tokens | B37: 3138 | C37: measured on gpt-5.4-mini
A38: Avg summary call: output tokens | B38: 86 | C38: measured on gpt-5.4-mini
A39: gpt-5.4 price $/1M: input / cached input / output | B39: 2.5 | C39: 0.25 | D39: 15
A40: Summary call on gpt-5.4 (estimate from measured tokens) | B40: =(B37*((1-B34)*B39+B34*C39)+B38*D39)/1000000
A42: OpenAI strategy (measured) | B42: $ per incident | C42: vs all-deep
A43: All gpt-5.4 (no routing, no semantic cache) | B43: =B35+B36+B40 | C43: =1-B43/$B$43
A44: Tiered routing (gpt-5.4 for P1/tier-1, mini otherwise) | B44: =$B$13*B31+(1-$B$13)*B32 | C44: =1-B44/$B$43
A45: Tiered routing + semantic cache (as built) | B45: =(1-$B$14)*B44+$B$14*B33 | C45: =1-B45/$B$43
A46: Measured costs already include retries and re-plans that happened, so no overhead multiplier is applied. The Claude rows above are modeled.

Sheet TCO
A1: Total cost of ownership
A3: Line ($ / month unless noted) | B3: Y1 | C3: Y2 | D3: Y3
A4: Incidents per month | B4: =Inputs!B5 | C4: =B4*(1+Inputs!$B$6) | D4: =C4*(1+Inputs!$B$6)
A5: Infrastructure subtotal | B5: =SUM(Inputs!B28:B35) | C5: =SUM(Inputs!C28:C35) | D5: =SUM(Inputs!D28:D35)
A6: LLM production (all incidents x measured cost per incident) | B6: =B4*'Token Economics'!$B$45 | C6: =C4*'Token Economics'!$B$45 | D6: =D4*'Token Economics'!$B$45
A7: LLM evaluation + staging | B7: =Inputs!$B$17 | C7: =Inputs!$B$17 | D7: =Inputs!$B$17
A8: Platform maintenance | B8: =Inputs!B16*Inputs!$B$4 | C8: =Inputs!C16*Inputs!$B$4 | D8: =Inputs!D16*Inputs!$B$4
A9: Total per month | B9: =SUM(B5:B8) | C9: =SUM(C5:C8) | D9: =SUM(D5:D8)
A10: Total per year | B10: =B9*12 | C10: =C9*12 | D10: =D9*12
A12: Year 0 (one-time)
A13: Capstone build (hours x rate) | B13: =Inputs!B22*Inputs!B4
A14: Productionization | B14: =Inputs!B23
A15: Landing zone + hardening | B15: =Inputs!B24
A16: Policy authoring + review | B16: =Inputs!B25
A17: Total Year 0 | B17: =SUM(B13:B16)

Sheet Benefits
A1: Benefits: SRE capacity freed (valued at the loaded rate, not headcount cuts)
A3: Line (per month unless noted) | B3: Y1 | C3: Y2 | D3: Y3
A4: Incidents through the platform | B4: =TCO!B4*Inputs!B7 | C4: =TCO!C4*Inputs!C7 | D4: =TCO!D4*Inputs!D7
A5: Automated incidents | B5: =B4*Inputs!B8 | C5: =C4*Inputs!C8 | D5: =D4*Inputs!D8
A6: HITL incidents | B6: =B4*Inputs!B9 | C6: =C4*Inputs!C9 | D6: =D4*Inputs!D9
A7: Escalated incidents | B7: =B4*Inputs!B10 | C7: =C4*Inputs!C10 | D7: =D4*Inputs!D10
A8: Minutes saved: automated | B8: =B5*Inputs!$B$11 | C8: =C5*Inputs!$B$11 | D8: =D5*Inputs!$B$11
A9: Minutes saved: HITL | B9: =B6*Inputs!$B$12 | C9: =C6*Inputs!$B$12 | D9: =D6*Inputs!$B$12
A10: Minutes saved: escalated | B10: =B7*Inputs!$B$13 | C10: =C7*Inputs!$B$13 | D10: =D7*Inputs!$B$13
A11: Bad-remediation cleanup (minutes) | B11: =-(B5+B6)*Inputs!B14*Inputs!$B$15 | C11: =-(C5+C6)*Inputs!C14*Inputs!$B$15 | D11: =-(D5+D6)*Inputs!D14*Inputs!$B$15
A12: Net minutes saved | B12: =SUM(B8:B11) | C12: =SUM(C8:C11) | D12: =SUM(D8:D11)
A13: SRE hours freed | B13: =B12/60 | C13: =C12/60 | D13: =D12/60
A14: Annual value ($ / year) | B14: =B13*12*Inputs!$B$4 | C14: =C13*12*Inputs!$B$4 | D14: =D13*12*Inputs!$B$4

Sheet Sensitivity
A1: Sensitivity: 3-year net
A3: Case | B3: 3-year net | C3: Change vs base
A4: Base | B4: =Summary!E8 | C4: =B4-$B$4
A5: Lower automation (points automated -> HITL, Inputs!B39) | B5: =B4-SUMPRODUCT(Benefits!B4:D4)*Inputs!B39*(Inputs!B11-Inputs!B12)*12/60*Inputs!B4 | C5: =B5-$B$4
A6: Slower adoption (Inputs row 40) | B6: =B4-(Benefits!B14*(1-Inputs!B40/Inputs!B7)+Benefits!C14*(1-Inputs!C40/Inputs!C7)+Benefits!D14*(1-Inputs!D40/Inputs!D7)) | C6: =B6-$B$4
A7: Lower volume (Inputs!B41 fewer incidents) | B7: =B4-Inputs!B41*Summary!C9+Inputs!B41*SUM(TCO!B6:D6)*12 | C7: =B7-$B$4
A8: LLM prices x2 | B8: =B4-SUM(TCO!B6:D7)*12 | C8: =B8-$B$4
A9: Productionization +50 % | B9: =B4-0.5*Inputs!B23 | C9: =B9-$B$4
A10: Azure warm DR | B10: =B4-Inputs!B19*36 | C10: =B10-$B$4
